MANIFEST.in
README.md
setup.cfg
setup.py
PyInABox/Login.sh
PyInABox/PyInABox.html
PyInABox/PyInABox.js
PyInABox/PyInABox.py
PyInABox.egg-info/PKG-INFO
PyInABox.egg-info/SOURCES.txt
PyInABox.egg-info/dependency_links.txt
PyInABox.egg-info/top_level.txt