Metadata-Version: 1.1
Name: PyInABox
Version: 1.0.1
Summary: Implementation of shell running on top of python-vte and Athena LivePage
Home-page: https://github.com/perkinslr/PyInABox
Author: Logan Perkins
Author-email: perkins@injeanieousdesigns.com
License: ZLIB
Keywords: vte COMET AJAX
Platform: UNKNOWN
Requires: zope.interface
Requires: nevow
